shape_existence/.DS_Store
shape_existence/__init__.py
shape_existence/complexes_and_proofs.py
shape_existence/flexible_cqp.py
shape_existence/fractions_and_interval_arithmetic.py
shape_existence/obj_stuff.py
shape_existence-0.0.5.dist-info/METADATA
shape_existence-0.0.5.dist-info/WHEEL
shape_existence-0.0.5.dist-info/licenses/LICENSE
shape_existence-0.0.5.dist-info/RECORD
