Metadata-Version: 2.1
Name: shape_existence
Version: 0.0.5
Summary: A package to prove the existence of non-intersecting realizations of abstract simplicial complexes with specified edge lengths.
Project-URL: Homepage, https://github.com/mve17/shape_existence
Project-URL: Bug Tracker, https://github.com/mve17/shape_existence/issues
Author-email: Matthew Ellison <matthew.v.ellison@gmail.com>
License-File: LICENSE
Classifier: License :: OSI Approved :: MIT License
Classifier: Operating System :: OS Independent
Classifier: Programming Language :: Python :: 3
Requires-Python: >=3.7
